nucliadb_models/__init__.py
nucliadb_models/augment.py
nucliadb_models/common.py
nucliadb_models/configuration.py
nucliadb_models/content_types.py
nucliadb_models/conversation.py
nucliadb_models/entities.py
nucliadb_models/export_import.py
nucliadb_models/external_index_providers.py
nucliadb_models/extracted.py
nucliadb_models/file.py
nucliadb_models/filters.py
nucliadb_models/hydration.py
nucliadb_models/labels.py
nucliadb_models/link.py
nucliadb_models/metadata.py
nucliadb_models/notifications.py
nucliadb_models/processing.py
nucliadb_models/py.typed
nucliadb_models/resource.py
nucliadb_models/retrieval.py
nucliadb_models/search.py
nucliadb_models/security.py
nucliadb_models/synonyms.py
nucliadb_models/text.py
nucliadb_models/trainset.py
nucliadb_models/utils.py
nucliadb_models/vectors.py
nucliadb_models/vectorsets.py
nucliadb_models/writer.py
nucliadb_models/agents/ingestion.py
nucliadb_models/graph/__init__.py
nucliadb_models/graph/requests.py
nucliadb_models/graph/responses.py
nucliadb_models/internal/__init__.py
nucliadb_models/internal/predict.py
nucliadb_models/internal/shards.py
nucliadb_models-6.11.1.post5854.dist-info/METADATA
nucliadb_models-6.11.1.post5854.dist-info/WHEEL
nucliadb_models-6.11.1.post5854.dist-info/top_level.txt
nucliadb_models-6.11.1.post5854.dist-info/RECORD
