Metadata-Version: 2.4
Name: nucliadb_models
Version: 6.11.1.post5854
Author-email: Nuclia <nucliadb@nuclia.com>
License-Expression: Apache-2.0
Project-URL: Homepage, https://nuclia.com
Project-URL: Repository, https://github.com/nuclia/nucliadb
Classifier: Development Status :: 4 - Beta
Classifier: Programming Language :: Python
Classifier: Programming Language :: Python :: 3.10
Classifier: Programming Language :: Python :: 3.11
Classifier: Programming Language :: Python :: 3.12
Classifier: Programming Language :: Python :: 3 :: Only
Classifier: Topic :: Software Development :: Libraries :: Python Modules
Requires-Python: <4,>=3.10
Requires-Dist: pydantic!=2.11.5,!=2.11.6,>=2.6
